pck_manojbudathoki/__init__.py
pck_manojbudathoki/mod.py
pck_manojbudathoki-0.0.1.dist-info/METADATA
pck_manojbudathoki-0.0.1.dist-info/WHEEL
pck_manojbudathoki-0.0.1.dist-info/RECORD
